fastadmin/__init__.py
fastadmin/api/__init__.py
fastadmin/api/exceptions.py
fastadmin/api/frameworks/__init__.py
fastadmin/api/frameworks/django/__init__.py
fastadmin/api/frameworks/django/app/__init__.py
fastadmin/api/frameworks/django/app/api.py
fastadmin/api/frameworks/django/app/urls.py
fastadmin/api/frameworks/django/app/views.py
fastadmin/api/frameworks/fastapi/__init__.py
fastadmin/api/frameworks/fastapi/api.py
fastadmin/api/frameworks/fastapi/app.py
fastadmin/api/frameworks/fastapi/views.py
fastadmin/api/frameworks/flask/__init__.py
fastadmin/api/frameworks/flask/api.py
fastadmin/api/frameworks/flask/app.py
fastadmin/api/frameworks/flask/views.py
fastadmin/api/helpers.py
fastadmin/api/schemas.py
fastadmin/api/service.py
fastadmin/models/__init__.py
fastadmin/models/base.py
fastadmin/models/decorators.py
fastadmin/models/helpers.py
fastadmin/models/orms/__init__.py
fastadmin/models/orms/django.py
fastadmin/models/orms/ponyorm.py
fastadmin/models/orms/sqlalchemy.py
fastadmin/models/orms/tortoise.py
fastadmin/models/schemas.py
fastadmin/settings.py
fastadmin/static/assets/worker-6Z7niv9l.js
fastadmin/static/assets/worker-C151k0-L.js
fastadmin/static/assets/worker-D3TWcJOI.js
fastadmin/static/assets/worker-MF2p-l5_.js
fastadmin/static/images/favicon.png
fastadmin/static/images/header-logo.svg
fastadmin/static/images/sign-in-logo.svg
fastadmin/static/index.html
fastadmin/static/index.min.css
fastadmin/static/index.min.js
fastadmin/templates/index.html
fastadmin_carbon-0.0.1.dist-info/LICENSE
fastadmin_carbon-0.0.1.dist-info/METADATA
fastadmin_carbon-0.0.1.dist-info/WHEEL
fastadmin_carbon-0.0.1.dist-info/RECORD
